tyson-0.1.3.dist-info/METADATA
tyson-0.1.3.dist-info/WHEEL
tyson/__init__.py
tyson/tyson.cpython-37m-x86_64-linux-gnu.so
tyson-0.1.3.dist-info/RECORD
