Metadata-Version: 2.1
Name: tyson
Version: 0.1.3
Classifier: Programming Language :: Rust
Classifier: Programming Language :: Python :: Implementation :: CPython
Classifier: Programming Language :: Python :: Implementation :: PyPy
Summary: Typed Simple Object Notation
Author: Roman Right <roman-right@protonmail.com>
Author-email: Roman Right <roman-right@protonmail.com>
License: Apache-2.0
Requires-Python: >=3.6
